README.md
license.txt
setup.cfg
setup.py
src/lcrmeter/__init__.py
src/lcrmeter/board.py
src/lcrmeter/file_handlers.py
src/lcrmeter/graph_plots.py
src/lcrmeter.egg-info/PKG-INFO
src/lcrmeter.egg-info/SOURCES.txt
src/lcrmeter.egg-info/dependency_links.txt
src/lcrmeter.egg-info/top_level.txt
src/lcrmeter/apps/__init__.py
src/lcrmeter/apps/sweeplist.py