Metadata-Version: 2.1
Name: lcrmeter
Version: 0.0.2
Summary: API for the Keysight E4980A LCR Meter
Home-page: https://github.imec.be/lockhart/lcrmeter
Author: César J. Lockhart de la Rosa
Author-email: lockhart@imec.be
License: MIT
Keywords: LCR Meter,impedance,api,keysight,E4980A
Platform: UNKNOWN
License-File: license.txt
